{
  "tableName": "ClientTestimonials",
  "exportedAt": "2026-06-20T13:22:32.005Z",
  "itemCount": 1,
  "items": [
    {
      "rating": 5,
      "updatedAt": "2026-06-18T11:23:22.189Z",
      "status": "active",
      "createdAt": "2026-05-12T06:49:12.064Z",
      "description": "Working with the team was a smooth experience. Communication was clear, delivery was on time, and the final result matched our expectations. We especially appreciated the attention to detail and support throughout the project.",
      "id": "8f7b249e-78a0-43c0-991b-9263703b8f61",
      "name": "Anurag",
      "profileImage": "client-testimonials/1781781801694-c0080071-c680-4604-bb02-34da6548b232.png"
    }
  ]
}